grinpy/__init__.py
grinpy/classes/__init__.py
grinpy/classes/functions.py
grinpy/classes/havel_hakimi.py
grinpy/functions/__init__.py
grinpy/functions/degree.py
grinpy/functions/distance.py
grinpy/functions/graph_operations.py
grinpy/functions/neighborhoods.py
grinpy/functions/structural_properties.py
grinpy/invariants/__init__.py
grinpy/invariants/chromatic.py
grinpy/invariants/clique.py
grinpy/invariants/disparity.py
grinpy/invariants/distance_measures.py
grinpy/invariants/domination.py
grinpy/invariants/dsi.py
grinpy/invariants/independence.py
grinpy/invariants/matching.py
grinpy/invariants/power_domination.py
grinpy/invariants/residue.py
grinpy/invariants/topological_indices.py
grinpy/invariants/vertex_cover.py
grinpy/invariants/zero_forcing.py
grinpy/utils/__init__.py
grinpy/utils/combinations.py
grinpy/utils/sequences.py
tests/__init__.py
tests/test_chromatic.py
tests/test_clique.py
tests/test_degree.py
tests/test_disparity.py
tests/test_distance_measures.py
tests/test_domination.py
tests/test_dsi.py
tests/test_functions.py
tests/test_graph_operations.py
tests/test_havel_hakimi.py
tests/test_independence.py
tests/test_matching.py
tests/test_neighborhoods.py
tests/test_power_domination.py
tests/test_residue.py
tests/test_structural_properties.py
tests/test_topological_indices.py
tests/test_vertex_cover.py
tests/test_zero_forcing.py
grinpy-19.7a0.dist-info/LICENSE.txt
grinpy-19.7a0.dist-info/METADATA
grinpy-19.7a0.dist-info/WHEEL
grinpy-19.7a0.dist-info/top_level.txt
grinpy-19.7a0.dist-info/RECORD
