Metadata-Version: 2.1
Name: grinpy
Version: 19.7a0
Summary: Graph invariants in Python.
Home-page: https://github.com/somacdivad/grinpy
Author: David Amos
Author-email: somacdivad@gmail.com
License: BSD license
Keywords: grinpy
Platform: UNKNOWN
Classifier: Development Status :: 2 - Pre-Alpha
Classifier: Intended Audience :: Science/Research
Classifier: Intended Audience :: Education
Classifier: License :: OSI Approved :: BSD License
Classifier: Operating System :: OS Independent
Classifier: Programming Language :: Python :: 3
Classifier: Programming Language :: Python :: 3.5
Classifier: Programming Language :: Python :: 3.6
Classifier: Programming Language :: Python :: 3.7
Classifier: Topic :: Scientific/Engineering :: Mathematics
Classifier: Topic :: Software Development :: Libraries :: Python Modules
Classifier: Natural Language :: English
Requires-Dist: networkx (>=2.1)
Requires-Dist: numpy (>=1.14.2)
Requires-Dist: pulp (>=1.6.8)
